pygw/__init__.py
pygw/config.py
pygw/debug.py
pygw/gateway.py
pygw/base/__init__.py
pygw/base/closeable_iterator.py
pygw/base/data_type_adapter.py
pygw/base/envelope.py
pygw/base/geowave_object.py
pygw/base/interval.py
pygw/base/java_transformer.py
pygw/base/range.py
pygw/base/type_conversions.py
pygw/base/write_results.py
pygw/base/writer.py
pygw/geotools/__init__.py
pygw/geotools/attribute_descriptor.py
pygw/geotools/feature_data_adapter.py
pygw/geotools/simple_feature.py
pygw/geotools/simple_feature_builder.py
pygw/geotools/simple_feature_type.py
pygw/geotools/simple_feature_type_builder.py
pygw/index/__init__.py
pygw/index/index.py
pygw/index/index_builder.py
pygw/index/spatial_index_builder.py
pygw/index/spatial_temporal_index_builder.py
pygw/query/__init__.py
pygw/query/aggregation_query.py
pygw/query/aggregation_query_builder.py
pygw/query/base_query_builder.py
pygw/query/query.py
pygw/query/query_builder.py
pygw/query/query_constraints.py
pygw/query/query_constraints_factory.py
pygw/query/query_hint_key.py
pygw/query/statistics/__init__.py
pygw/query/statistics/statistic_query.py
pygw/query/statistics/statistic_query_builder.py
pygw/query/vector/__init__.py
pygw/query/vector/filter_factory.py
pygw/query/vector/spatial_temporal_constraints_builder.py
pygw/query/vector/vector_aggregation_query_builder.py
pygw/query/vector/vector_query_builder.py
pygw/query/vector/vector_query_constraints_factory.py
pygw/statistics/__init__.py
pygw/statistics/bin_constraints.py
pygw/statistics/binning_strategy_mappings.py
pygw/statistics/statistic.py
pygw/statistics/statistic_binning_strategy.py
pygw/statistics/statistic_mappings.py
pygw/statistics/statistic_type.py
pygw/statistics/statistic_value.py
pygw/statistics/transformers.py
pygw/statistics/binning_strategy/__init__.py
pygw/statistics/binning_strategy/composite_binning_strategy.py
pygw/statistics/binning_strategy/data_type_binning_strategy.py
pygw/statistics/binning_strategy/field_value_binning_strategy.py
pygw-2.0.1.dist-info/LICENSE
pygw-2.0.1.dist-info/METADATA
pygw-2.0.1.dist-info/WHEEL
pygw-2.0.1.dist-info/top_level.txt
pygw-2.0.1.dist-info/RECORD
