Metadata-Version: 2.1
Name: pygw
Version: 2.0.1
Summary: GeoWave bindings for Python3
Home-page: https://locationtech.github.io/geowave/
Author: GeoWave Contributors
Author-email: geowave.python@gmail.com
License: UNKNOWN
Project-URL: Documentation, https://locationtech.github.io/geowave/pydocs/
Project-URL: Source, https://github.com/locationtech/geowave/tree/master/python/src/main/python
Platform: UNKNOWN
Classifier: Programming Language :: Python :: 3
Classifier: Programming Language :: Python :: 3.0
Classifier: Programming Language :: Python :: 3.1
Classifier: Programming Language :: Python :: 3.2
Classifier: Programming Language :: Python :: 3.3
Classifier: Programming Language :: Python :: 3.4
Classifier: Programming Language :: Python :: 3.5
Classifier: Programming Language :: Python :: 3.6
Classifier: Programming Language :: Python :: 3.7
Classifier: License :: OSI Approved :: Apache Software License
Classifier: Operating System :: OS Independent
Requires-Python: >=3,<3.8
License-File: LICENSE
Requires-Dist: py4j (==0.10.8.1)
Requires-Dist: shapely (==1.7)
